[
    {
        "BannerName": "贸易契约",
        "OpenTime": "",
        "CloseTime": "",
        "Device": 0,
        "PictureName": "gameActivity5",
        "LinkPage": 6,
        "ID": 1,
        "Name": null
    },
    {
        "BannerName": "七日登录",
        "OpenTime": "",
        "CloseTime": "",
        "Device": 0,
        "PictureName": "gameActivity2",
        "LinkPage": 7,
        "ID": 2,
        "Name": null
    },
    {
        "BannerName": "伊芙琳剧情",
        "OpenTime": "",
        "CloseTime": "",
        "Device": 0,
        "PictureName": "gameActivity3",
        "LinkPage": 8,
        "ID": 3,
        "Name": null
    },
    {
        "BannerName": "皮肤特惠",
        "OpenTime": "2019/7/18 00:00:00",
        "CloseTime": "2019/8/13 13:59:59",
        "Device": 0,
        "PictureName": "gameActivity6",
        "LinkPage": 1,
        "ID": 4,
        "Name": null
    },
    {
        "BannerName": "累计充值",
        "OpenTime": "",
        "CloseTime": "",
        "Device": 0,
        "PictureName": "gameActivity4",
        "LinkPage": 2,
        "ID": 5,
        "Name": null
    },
    {
        "BannerName": "十连招募-艾莉克萨",
        "OpenTime": "2019/7/18 00:00:00",
        "CloseTime": "2019/7/30 13:59:59",
        "Device": 0,
        "PictureName": "gameActivity7",
        "LinkPage": 3,
        "ID": 6,
        "Name": null
    },
    {
        "BannerName": "十连开发-伊利希斯",
        "OpenTime": "2019/7/18 00:00:00",
        "CloseTime": "2019/7/30 13:59:59",
        "Device": 0,
        "PictureName": "gameActivity9",
        "LinkPage": 4,
        "ID": 7,
        "Name": null
    },
    {
        "BannerName": "十连招募-九条绫",
        "OpenTime": "2019/7/30 14:00:00",
        "CloseTime": "2019/8/13 13:59:59",
        "Device": 0,
        "PictureName": "gameActivity8",
        "LinkPage": 3,
        "ID": 8,
        "Name": null
    },
    {
        "BannerName": "十连开发-α-16",
        "OpenTime": "2019/7/30 14:00:00",
        "CloseTime": "2019/8/13 13:59:59",
        "Device": 0,
        "PictureName": "gameActivity10",
        "LinkPage": 4,
        "ID": 9,
        "Name": null
    },
    {
        "BannerName": "克尔贝洛之影",
        "OpenTime": "2019/7/30 14:00:00",
        "CloseTime": "2019/8/13 13:59:59",
        "Device": 0,
        "PictureName": "gameActivity1",
        "LinkPage": 5,
        "ID": 10,
        "Name": null
    },
    {
        "BannerName": "贸易契约",
        "OpenTime": "",
        "CloseTime": "",
        "Device": 1,
        "PictureName": "gameActivity5",
        "LinkPage": 6,
        "ID": 11,
        "Name": null
    },
    {
        "BannerName": "七日登录",
        "OpenTime": "",
        "CloseTime": "",
        "Device": 1,
        "PictureName": "gameActivity2",
        "LinkPage": 7,
        "ID": 12,
        "Name": null
    },
    {
        "BannerName": "伊芙琳剧情",
        "OpenTime": "",
        "CloseTime": "",
        "Device": 1,
        "PictureName": "gameActivity3",
        "LinkPage": 8,
        "ID": 13,
        "Name": null
    },
    {
        "BannerName": "皮肤特惠",
        "OpenTime": "2019/7/16 00:00:00",
        "CloseTime": "2019/8/13 13:59:59",
        "Device": 1,
        "PictureName": "gameActivity6",
        "LinkPage": 1,
        "ID": 14,
        "Name": null
    },
    {
        "BannerName": "累计充值",
        "OpenTime": "",
        "CloseTime": "",
        "Device": 1,
        "PictureName": "gameActivity4",
        "LinkPage": 2,
        "ID": 15,
        "Name": null
    },
    {
        "BannerName": "十连招募-艾莉克萨",
        "OpenTime": "2019/7/16 00:00:00",
        "CloseTime": "2019/7/30 13:59:59",
        "Device": 1,
        "PictureName": "gameActivity7",
        "LinkPage": 3,
        "ID": 16,
        "Name": null
    },
    {
        "BannerName": "十连开发-伊利希斯",
        "OpenTime": "2019/7/16 00:00:00",
        "CloseTime": "2019/7/30 13:59:59",
        "Device": 1,
        "PictureName": "gameActivity9",
        "LinkPage": 4,
        "ID": 17,
        "Name": null
    },
    {
        "BannerName": "十连招募-九条绫",
        "OpenTime": "2019/7/30 14:00:00",
        "CloseTime": "2019/8/13 13:59:59",
        "Device": 1,
        "PictureName": "gameActivity8",
        "LinkPage": 3,
        "ID": 18,
        "Name": null
    },
    {
        "BannerName": "十连开发-α-16",
        "OpenTime": "2019/7/30 14:00:00",
        "CloseTime": "2019/8/13 13:59:59",
        "Device": 1,
        "PictureName": "gameActivity10",
        "LinkPage": 4,
        "ID": 19,
        "Name": null
    },
    {
        "BannerName": "克尔贝洛之影",
        "OpenTime": "2019/7/30 14:00:00",
        "CloseTime": "2019/8/13 13:59:59",
        "Device": 1,
        "PictureName": "gameActivity1",
        "LinkPage": 5,
        "ID": 20,
        "Name": null
    }
]