[
    {
        "UserLevel": 1,
        "UserExp": 24,
        "ID": 1,
        "Name": null
    },
    {
        "UserLevel": 2,
        "UserExp": 45,
        "ID": 2,
        "Name": null
    },
    {
        "UserLevel": 3,
        "UserExp": 79,
        "ID": 3,
        "Name": null
    },
    {
        "UserLevel": 4,
        "UserExp": 131,
        "ID": 4,
        "Name": null
    },
    {
        "UserLevel": 5,
        "UserExp": 201,
        "ID": 5,
        "Name": null
    },
    {
        "UserLevel": 6,
        "UserExp": 293,
        "ID": 6,
        "Name": null
    },
    {
        "UserLevel": 7,
        "UserExp": 409,
        "ID": 7,
        "Name": null
    },
    {
        "UserLevel": 8,
        "UserExp": 552,
        "ID": 8,
        "Name": null
    },
    {
        "UserLevel": 9,
        "UserExp": 725,
        "ID": 9,
        "Name": null
    },
    {
        "UserLevel": 10,
        "UserExp": 931,
        "ID": 10,
        "Name": null
    },
    {
        "UserLevel": 11,
        "UserExp": 1172,
        "ID": 11,
        "Name": null
    },
    {
        "UserLevel": 12,
        "UserExp": 1451,
        "ID": 12,
        "Name": null
    },
    {
        "UserLevel": 13,
        "UserExp": 1771,
        "ID": 13,
        "Name": null
    },
    {
        "UserLevel": 14,
        "UserExp": 2135,
        "ID": 14,
        "Name": null
    },
    {
        "UserLevel": 15,
        "UserExp": 2545,
        "ID": 15,
        "Name": null
    },
    {
        "UserLevel": 16,
        "UserExp": 3004,
        "ID": 16,
        "Name": null
    },
    {
        "UserLevel": 17,
        "UserExp": 3516,
        "ID": 17,
        "Name": null
    },
    {
        "UserLevel": 18,
        "UserExp": 4083,
        "ID": 18,
        "Name": null
    },
    {
        "UserLevel": 19,
        "UserExp": 4708,
        "ID": 19,
        "Name": null
    },
    {
        "UserLevel": 20,
        "UserExp": 5394,
        "ID": 20,
        "Name": null
    },
    {
        "UserLevel": 21,
        "UserExp": 6144,
        "ID": 21,
        "Name": null
    },
    {
        "UserLevel": 22,
        "UserExp": 6961,
        "ID": 22,
        "Name": null
    },
    {
        "UserLevel": 23,
        "UserExp": 7847,
        "ID": 23,
        "Name": null
    },
    {
        "UserLevel": 24,
        "UserExp": 8807,
        "ID": 24,
        "Name": null
    },
    {
        "UserLevel": 25,
        "UserExp": 9842,
        "ID": 25,
        "Name": null
    },
    {
        "UserLevel": 26,
        "UserExp": 10956,
        "ID": 26,
        "Name": null
    },
    {
        "UserLevel": 27,
        "UserExp": 12152,
        "ID": 27,
        "Name": null
    },
    {
        "UserLevel": 28,
        "UserExp": 13433,
        "ID": 28,
        "Name": null
    },
    {
        "UserLevel": 29,
        "UserExp": 14803,
        "ID": 29,
        "Name": null
    },
    {
        "UserLevel": 30,
        "UserExp": 16263,
        "ID": 30,
        "Name": null
    },
    {
        "UserLevel": 31,
        "UserExp": 17818,
        "ID": 31,
        "Name": null
    },
    {
        "UserLevel": 32,
        "UserExp": 19470,
        "ID": 32,
        "Name": null
    },
    {
        "UserLevel": 33,
        "UserExp": 21223,
        "ID": 33,
        "Name": null
    },
    {
        "UserLevel": 34,
        "UserExp": 23079,
        "ID": 34,
        "Name": null
    },
    {
        "UserLevel": 35,
        "UserExp": 25043,
        "ID": 35,
        "Name": null
    },
    {
        "UserLevel": 36,
        "UserExp": 27117,
        "ID": 36,
        "Name": null
    },
    {
        "UserLevel": 37,
        "UserExp": 29304,
        "ID": 37,
        "Name": null
    },
    {
        "UserLevel": 38,
        "UserExp": 31608,
        "ID": 38,
        "Name": null
    },
    {
        "UserLevel": 39,
        "UserExp": 34031,
        "ID": 39,
        "Name": null
    },
    {
        "UserLevel": 40,
        "UserExp": 36579,
        "ID": 40,
        "Name": null
    },
    {
        "UserLevel": 41,
        "UserExp": 39252,
        "ID": 41,
        "Name": null
    },
    {
        "UserLevel": 42,
        "UserExp": 42055,
        "ID": 42,
        "Name": null
    },
    {
        "UserLevel": 43,
        "UserExp": 44992,
        "ID": 43,
        "Name": null
    },
    {
        "UserLevel": 44,
        "UserExp": 48065,
        "ID": 44,
        "Name": null
    },
    {
        "UserLevel": 45,
        "UserExp": 51278,
        "ID": 45,
        "Name": null
    },
    {
        "UserLevel": 46,
        "UserExp": 54634,
        "ID": 46,
        "Name": null
    },
    {
        "UserLevel": 47,
        "UserExp": 58137,
        "ID": 47,
        "Name": null
    },
    {
        "UserLevel": 48,
        "UserExp": 61791,
        "ID": 48,
        "Name": null
    },
    {
        "UserLevel": 49,
        "UserExp": 65597,
        "ID": 49,
        "Name": null
    },
    {
        "UserLevel": 50,
        "UserExp": 69561,
        "ID": 50,
        "Name": null
    },
    {
        "UserLevel": 51,
        "UserExp": 73685,
        "ID": 51,
        "Name": null
    },
    {
        "UserLevel": 52,
        "UserExp": 77974,
        "ID": 52,
        "Name": null
    },
    {
        "UserLevel": 53,
        "UserExp": 82429,
        "ID": 53,
        "Name": null
    },
    {
        "UserLevel": 54,
        "UserExp": 87056,
        "ID": 54,
        "Name": null
    },
    {
        "UserLevel": 55,
        "UserExp": 91858,
        "ID": 55,
        "Name": null
    },
    {
        "UserLevel": 56,
        "UserExp": 96838,
        "ID": 56,
        "Name": null
    },
    {
        "UserLevel": 57,
        "UserExp": 101999,
        "ID": 57,
        "Name": null
    },
    {
        "UserLevel": 58,
        "UserExp": 107346,
        "ID": 58,
        "Name": null
    },
    {
        "UserLevel": 59,
        "UserExp": 112882,
        "ID": 59,
        "Name": null
    },
    {
        "UserLevel": 60,
        "UserExp": 118611,
        "ID": 60,
        "Name": null
    }
]