[
    {
        "StageId": 8132,
        "StageIds": [
            8132,
            8144,
            8145,
            8146,
            8147
        ],
        "ID": 1,
        "Name": null
    },
    {
        "StageId": 8133,
        "StageIds": [
            8133,
            8148,
            8149,
            8150,
            8151
        ],
        "ID": 2,
        "Name": null
    },
    {
        "StageId": 8134,
        "StageIds": [
            8134,
            8152,
            8153,
            8154,
            8155
        ],
        "ID": 3,
        "Name": null
    },
    {
        "StageId": 8135,
        "StageIds": [
            8135,
            8156,
            8157,
            8158,
            8159
        ],
        "ID": 4,
        "Name": null
    },
    {
        "StageId": 8136,
        "StageIds": [
            8136,
            8160,
            8161,
            8162,
            8163
        ],
        "ID": 5,
        "Name": null
    },
    {
        "StageId": 8137,
        "StageIds": [
            8137,
            8164,
            8165,
            8166,
            8167
        ],
        "ID": 6,
        "Name": null
    },
    {
        "StageId": 8138,
        "StageIds": [
            8138,
            8168,
            8169,
            8170,
            8171
        ],
        "ID": 7,
        "Name": null
    },
    {
        "StageId": 8139,
        "StageIds": [
            8139,
            8172,
            8173,
            8174,
            8175
        ],
        "ID": 8,
        "Name": null
    },
    {
        "StageId": 8140,
        "StageIds": [
            8140,
            8176,
            8177,
            8178,
            8179
        ],
        "ID": 9,
        "Name": null
    }
]